jax_bigvgan/__init__.py
jax_bigvgan/convert.py
jax_bigvgan/infer.py
jax_bigvgan/models.py
jax_bigvgan/util.py
jax_bigvgan-0.0.8.dist-info/METADATA
jax_bigvgan-0.0.8.dist-info/WHEEL
jax_bigvgan-0.0.8.dist-info/top_level.txt
jax_bigvgan-0.0.8.dist-info/RECORD
