Metadata-Version: 2.2
Name: jax-bigvgan
Version: 0.0.8
Summary: JAX Implementation BigVGAN
Author-email: flyingblackshark <aliu2000@outlook.com>
Project-URL: Homepage, https://github.com/flyingblackshark/jax-BigVGAN
Project-URL: Issues, https://github.com/flyingblackshark/jax-BigVGAN/issues
Classifier: Development Status :: 5 - Production/Stable
Classifier: Intended Audience :: Developers
Classifier: Intended Audience :: Education
Classifier: Intended Audience :: Science/Research
Classifier: License :: OSI Approved :: MIT License
Classifier: Topic :: Scientific/Engineering :: Mathematics
Classifier: Topic :: Scientific/Engineering :: Artificial Intelligence
Classifier: Topic :: Software Development :: Libraries :: Python Modules
Classifier: Topic :: System :: Distributed Computing
Classifier: Programming Language :: Python :: 3
Requires-Python: >=3.8
Requires-Dist: jax>=0.2.16
Requires-Dist: flax
Requires-Dist: torch
